aaopto_aotf/__init__.py
aaopto_aotf/aotf.py
aaopto_aotf/device_codes.py
aaopto_aotf-0.0.11.dist-info/LICENSE
aaopto_aotf-0.0.11.dist-info/METADATA
aaopto_aotf-0.0.11.dist-info/WHEEL
aaopto_aotf-0.0.11.dist-info/top_level.txt
aaopto_aotf-0.0.11.dist-info/RECORD
