Metadata-Version: 2.1
Name: aaopto_aotf
Version: 0.0.11
Summary: Python driver for AA OptoElectronics AOTF device.
Author: Allen Institute for Neural Dynamics
License: MIT
Classifier: Programming Language :: Python :: 3
Requires-Python: >=3.6
License-File: LICENSE
Requires-Dist: pyserial
Requires-Dist: parse
Provides-Extra: dev
Requires-Dist: matplotlib ; extra == 'dev'
Requires-Dist: numpy ; extra == 'dev'
Requires-Dist: thorlabs-apt ; extra == 'dev'
Requires-Dist: tqdm ; extra == 'dev'
Requires-Dist: black ; extra == 'dev'
Requires-Dist: coverage ; extra == 'dev'
Requires-Dist: flake8 ; extra == 'dev'
Requires-Dist: interrogate ; extra == 'dev'
Requires-Dist: isort ; extra == 'dev'
Requires-Dist: Sphinx ; extra == 'dev'
Requires-Dist: enum-tools[sphinx] ; extra == 'dev'
Requires-Dist: pygit2 ; extra == 'dev'
Requires-Dist: furo ; extra == 'dev'
